flask_check_json/__init__.py
flask_check_json/decorator/__init__.py
flask_check_json/extensions/__init__.py
flask_check_json/validator/__init__.py
flask_check_json-0.1.7.dist-info/LICENSE.txt
flask_check_json-0.1.7.dist-info/METADATA
flask_check_json-0.1.7.dist-info/WHEEL
flask_check_json-0.1.7.dist-info/top_level.txt
flask_check_json-0.1.7.dist-info/RECORD
